pytz/__init__.py
pytz/exceptions.py
pytz/lazy.py
pytz/reference.py
pytz/tzfile.py
pytz/tzinfo.py
pytz/zoneinfo/CET
pytz/zoneinfo/CST6CDT
pytz/zoneinfo/Cuba
pytz/zoneinfo/EET
pytz/zoneinfo/EST
pytz/zoneinfo/EST5EDT
pytz/zoneinfo/Egypt
pytz/zoneinfo/Eire
pytz/zoneinfo/Factory
pytz/zoneinfo/GB
pytz/zoneinfo/GB-Eire
pytz/zoneinfo/GMT
pytz/zoneinfo/GMT+0
pytz/zoneinfo/GMT-0
pytz/zoneinfo/GMT0
pytz/zoneinfo/Greenwich
pytz/zoneinfo/HST
pytz/zoneinfo/Hongkong
pytz/zoneinfo/Iceland
pytz/zoneinfo/Iran
pytz/zoneinfo/Israel
pytz/zoneinfo/Jamaica
pytz/zoneinfo/Japan
pytz/zoneinfo/Kwajalein
pytz/zoneinfo/Libya
pytz/zoneinfo/MET
pytz/zoneinfo/MST
pytz/zoneinfo/MST7MDT
pytz/zoneinfo/NZ
pytz/zoneinfo/NZ-CHAT
pytz/zoneinfo/Navajo
pytz/zoneinfo/PRC
pytz/zoneinfo/PST8PDT
pytz/zoneinfo/Poland
pytz/zoneinfo/Portugal
pytz/zoneinfo/ROC
pytz/zoneinfo/ROK
pytz/zoneinfo/Singapore
pytz/zoneinfo/Turkey
pytz/zoneinfo/UCT
pytz/zoneinfo/UTC
pytz/zoneinfo/Universal
pytz/zoneinfo/W-SU
pytz/zoneinfo/WET
pytz/zoneinfo/Zulu
pytz/zoneinfo/iso3166.tab
pytz/zoneinfo/leapseconds
pytz/zoneinfo/tzdata.zi
pytz/zoneinfo/zone.tab
pytz/zoneinfo/zone1970.tab
pytz/zoneinfo/zonenow.tab
pytz/zoneinfo/Africa/Abidjan
pytz/zoneinfo/Africa/Accra
pytz/zoneinfo/Africa/Addis_Ababa
pytz/zoneinfo/Africa/Algiers
pytz/zoneinfo/Africa/Asmara
pytz/zoneinfo/Africa/Asmera
pytz/zoneinfo/Africa/Bamako
pytz/zoneinfo/Africa/Bangui
pytz/zoneinfo/Africa/Banjul
pytz/zoneinfo/Africa/Bissau
pytz/zoneinfo/Africa/Blantyre
pytz/zoneinfo/Africa/Brazzaville
pytz/zoneinfo/Africa/Bujumbura
pytz/zoneinfo/Africa/Cairo
pytz/zoneinfo/Africa/Casablanca
pytz/zoneinfo/Africa/Ceuta
pytz/zoneinfo/Africa/Conakry
pytz/zoneinfo/Africa/Dakar
pytz/zoneinfo/Africa/Dar_es_Salaam
pytz/zoneinfo/Africa/Djibouti
pytz/zoneinfo/Africa/Douala
pytz/zoneinfo/Africa/El_Aaiun
pytz/zoneinfo/Africa/Freetown
pytz/zoneinfo/Africa/Gaborone
pytz/zoneinfo/Africa/Harare
pytz/zoneinfo/Africa/Johannesburg
pytz/zoneinfo/Africa/Juba
pytz/zoneinfo/Africa/Kampala
pytz-2023.4.dist-info/LICENSE.txt
pytz-2023.4.dist-info/METADATA
pytz-2023.4.dist-info/WHEEL
pytz-2023.4.dist-info/top_level.txt
pytz-2023.4.dist-info/zip-safe
pytz-2023.4.dist-info/RECORD
